FlexTest/__init__.py
flextest-1.0.1.dist-info/LICENSE
flextest-1.0.1.dist-info/METADATA
flextest-1.0.1.dist-info/WHEEL
flextest-1.0.1.dist-info/RECORD
